sfs/__init__.py
sfs/cli.py
sfs/config.py
sfs/core.py
sfs/events.py
sfs/exceptions.py
sfs/file_system.py
sfs/helper.py
sfs/log_utils.py
sfs/ops/__init__.py
sfs/ops/helper.py
sfs/ops/ops_collection.py
sfs/ops/ops_dedup.py
sfs/ops/ops_main.py
sfs/ops/ops_merge.py
sfs/ops/ops_query.py
Symbolic_File_System-2.0.0.dist-info/LICENSE
Symbolic_File_System-2.0.0.dist-info/METADATA
Symbolic_File_System-2.0.0.dist-info/WHEEL
Symbolic_File_System-2.0.0.dist-info/entry_points.txt
Symbolic_File_System-2.0.0.dist-info/top_level.txt
Symbolic_File_System-2.0.0.dist-info/RECORD
