Metadata-Version: 2.1
Name: Symbolic-File-System
Version: 2.0.0
Summary: Lightweight file manager for backing up and organizing your data
Home-page: UNKNOWN
Author: Rohit Biswas
Author-email: biswasrohit143@gmail.com
License: MIT
Keywords: symbolic-links file-system organize backup utility
Platform: UNKNOWN
Classifier: Development Status :: 2 - Pre-Alpha
Classifier: Environment :: Console
Classifier: Intended Audience :: End Users/Desktop
Classifier: License :: OSI Approved :: MIT License
Classifier: Operating System :: POSIX :: Linux
Classifier: Programming Language :: Python :: 3 :: Only
Classifier: Topic :: System :: Filesystems
Classifier: Topic :: Utilities
Requires-Python: >=3
